pygrinder/__init__.py
pygrinder/utils.py
pygrinder/version.py
pygrinder/block_missing/__init__.py
pygrinder/block_missing/block_missing.py
pygrinder/missing_at_random/__init__.py
pygrinder/missing_at_random/mar_logistic.py
pygrinder/missing_completely_at_random/__init__.py
pygrinder/missing_completely_at_random/little_test.py
pygrinder/missing_completely_at_random/mcar.py
pygrinder/missing_not_at_random/__init__.py
pygrinder/missing_not_at_random/mnar_t.py
pygrinder/missing_not_at_random/mnar_x.py
pygrinder/randomly_drop_observations/__init__.py
pygrinder/randomly_drop_observations/rdo.py
pygrinder/sequential_missing/__init__.py
pygrinder/sequential_missing/seq_missing.py
pygrinder-0.6.4.dist-info/LICENSE
pygrinder-0.6.4.dist-info/METADATA
pygrinder-0.6.4.dist-info/WHEEL
pygrinder-0.6.4.dist-info/top_level.txt
pygrinder-0.6.4.dist-info/RECORD
