Metadata-Version: 2.1
Name: pygrinder
Version: 0.6.4
Summary: A Python toolkit for introducing missing values into datasets
Author-email: Wenjie Du <wenjay.du@gmail.com>
License: Copyright (c) 2023-present, Wenjie Du
Project-URL: Source, https://github.com/WenjieDu/PyGrinder
Project-URL: Homepage, https://pypots.com
Project-URL: Documentation, https://docs.pypots.com
Project-URL: Bug Tracker, https://github.com/WenjieDu/PyGrinder/issues
Project-URL: Download, https://github.com/WenjieDu/PyGrinder/archive/main.zip
Keywords: data corruption,incomplete data,data mining,pypots,missingness,partially observed,irregular sampled,partially-observed time series,incomplete time series,missing data,missing values,simulation,pypots
Classifier: Development Status :: 5 - Production/Stable
Classifier: Intended Audience :: Developers
Classifier: Intended Audience :: Education
Classifier: Intended Audience :: Science/Research
Classifier: License :: OSI Approved :: BSD License
Classifier: Operating System :: OS Independent
Classifier: Programming Language :: Python :: 3
Classifier: Topic :: Scientific/Engineering :: Artificial Intelligence
Classifier: Topic :: Software Development :: Libraries :: Application Frameworks
Requires-Python: >=3.8
License-File: LICENSE
Requires-Dist: numpy
Requires-Dist: scikit-learn
Requires-Dist: pandas
Requires-Dist: torch
Requires-Dist: tsdb
